counterfactuals/__init__.py
counterfactuals/counterfactualprogram.py
counterfactuals/main.py
counterfactuals-1.0.2.dist-info/LICENCE
counterfactuals-1.0.2.dist-info/METADATA
counterfactuals-1.0.2.dist-info/WHEEL
counterfactuals-1.0.2.dist-info/entry_points.txt
counterfactuals-1.0.2.dist-info/top_level.txt
counterfactuals-1.0.2.dist-info/RECORD
