Metadata-Version: 2.1
Name: counterfactuals
Version: 1.0.2
Summary: A solver for Counterfactual Inference.
Author: R. Kiesel
Author-email: rafael.kiesel@tuwien.ac.at
License: MIT
Keywords: probabilistic,logic programming,counterfactual reasoning
Classifier: Development Status :: 4 - Beta
Classifier: Topic :: Scientific/Engineering
Classifier: Topic :: Scientific/Engineering :: Artificial Intelligence
Classifier: License :: OSI Approved :: MIT License
Classifier: Programming Language :: Python :: 3
Classifier: Programming Language :: Python :: 3.6
Classifier: Programming Language :: Python :: 3.7
Classifier: Programming Language :: Python :: 3.8
Classifier: Programming Language :: Python :: 3.9
Classifier: Programming Language :: Python :: 3.10
Classifier: Programming Language :: Python :: 3 :: Only
Requires-Python: >=3.6, <4
License-File: LICENCE
Requires-Dist: aspmc
Requires-Dist: PySDD
